pxd_combinable_groups
